CHANGES.rst
LICENSE.txt
MANIFEST.in
README.rst
setup.cfg
setup.py
relshell/__init__.py
relshell/base_shelloperator.py
relshell/batch.py
relshell/batch_command.py
relshell/batch_from_file.py
relshell/batch_to_file.py
relshell/batch_to_from_file.py
relshell/columndef.py
relshell/daemon_shelloperator.py
relshell/logger.py
relshell/record.py
relshell/recorddef.py
relshell/shelloperator.py
relshell/timespan.py
relshell/timestamp.py
relshell/type.py
relshell.egg-info/PKG-INFO
relshell.egg-info/SOURCES.txt
relshell.egg-info/dependency_links.txt
relshell.egg-info/requires.txt
relshell.egg-info/top_level.txt
relshell/test/__init__.py
relshell/test/test_batch.py
relshell/test/test_batch_command.py
relshell/test/test_daemon_shelloperator.py
relshell/test/test_practicaluse_01.py
relshell/test/test_practicaluse_02.py
relshell/test/test_record.py
relshell/test/test_recorddef.py
relshell/test/test_shelloperator.py
relshell/test/test_timestamp.py
relshell/test/test_type.py