Metadata-Version: 1.1
Name: relshell
Version: 0.3.3
Summary: A framework to manage shell commands' inputs/outputs as relational data.
Home-page: https://github.com/laysakura/relshell
Author: Sho Nakatani
Author-email: lay.sakura@gmail.com
License: LICENSE.txt
Platform: UNKNOWN
Classifier: Programming Language :: Python
Classifier: Development Status :: 4 - Beta
Classifier: License :: OSI Approved :: Apache Software License
Classifier: Programming Language :: Python :: 2.6
Classifier: Programming Language :: Python :: 2.7
Classifier: Programming Language :: Python :: Implementation :: PyPy
Classifier: Operating System :: POSIX :: Linux
